[
  {
    "id": "54de25",
    "text": "Description: Implement `grove cycle` command for cycling through running servers in browser.\n\nFrom spec section 12.6:\n- Cycles through all running servers in default browser\n- Each invocation opens the next server URL\n- Wraps around to first\n\nImplementation:\n- Store \"current index\" in temp file (~/.cache/grove/cycle-index)\n- Increment on each call, wrap at end\n- Open URL in default browser",
    "created_at": "2026-01-05T19:20:37.079109Z"
  },
  {
    "id": "fe6b9f",
    "text": "Close reason: Implemented all Phase 4b features: grove review, grove cycle, and grove dashboard with SvelteKit web UI",
    "created_at": "2026-01-05T19:20:37.079175Z"
  }
]